qlist/__init__.py
qlist/qlist.py
qlist-0.0.1.dist-info/LICENSE
qlist-0.0.1.dist-info/METADATA
qlist-0.0.1.dist-info/WHEEL
qlist-0.0.1.dist-info/top_level.txt
qlist-0.0.1.dist-info/RECORD
